LICENSE.md
MANIFEST.in
README.rst
pyproject.toml
requirements.core.txt
requirements.txt
setup.py
core_module_local_id_registry_app/__init__.py
core_module_local_id_registry_app/settings.py
core_module_local_id_registry_app/urls.py
core_module_local_id_registry_app.egg-info/PKG-INFO
core_module_local_id_registry_app.egg-info/SOURCES.txt
core_module_local_id_registry_app.egg-info/dependency_links.txt
core_module_local_id_registry_app.egg-info/requires.txt
core_module_local_id_registry_app.egg-info/top_level.txt
core_module_local_id_registry_app/static/core_module_local_id_registry_app/css/module_local_id.css
core_module_local_id_registry_app/static/core_module_local_id_registry_app/js/module_local_id.js
core_module_local_id_registry_app/templates/core_module_local_id_registry_app/pid_display_box.html
core_module_local_id_registry_app/templates/core_module_local_id_registry_app/pid_edit_input.html
core_module_local_id_registry_app/views/__init__.py
core_module_local_id_registry_app/views/views.py
tests/__init__.py
tests/test_settings.py
tests/views/__init__.py
tests/views/LocalIdRegistryModule/__init__.py
tests/views/LocalIdRegistryModule/fixtures.py
tests/views/LocalIdRegistryModule/test_unit.py