Metadata-Version: 2.1
Name: core-module-local-id-registry-app
Version: 2.19.0
Summary: Local id registry module
Home-page: https://github.com/usnistgov/core_module_local_id_registry_app
Author: NIST IT Lab
Author-email: itl_inquiries@nist.gov
License-File: LICENSE.md
